{"mean":{"confidence_interval":{"confidence_level":0.95,"lower_bound":736.1751402083031,"upper_bound":739.6913003827812},"point_estimate":737.9108428507845,"standard_error":0.9018430004072999},"median":{"confidence_interval":{"confidence_level":0.95,"lower_bound":734.8997881994202,"upper_bound":740.7999843701746},"point_estimate":738.7999918043977,"standard_error":1.5912158663640998},"median_abs_dev":{"confidence_interval":{"confidence_level":0.95,"lower_bound":8.264471714405294,"upper_bound":12.222963046069301},"point_estimate":10.701987976940117,"standard_error":1.0452220970937787},"slope":{"confidence_interval":{"confidence_level":0.95,"lower_bound":733.1326868540934,"upper_bound":737.1523082847891},"point_estimate":735.0901145390508,"standard_error":1.0285734084565963},"std_dev":{"confidence_interval":{"confidence_level":0.95,"lower_bound":7.8817068486646065,"upper_bound":9.999159198091872},"point_estimate":8.98347243983003,"standard_error":0.5395485095895839}}